pygpib/__init__.py
pygpib/agilent_82357a.py
pygpib/gpib.py
pygpib-0.0.0.dist-info/METADATA
pygpib-0.0.0.dist-info/WHEEL
pygpib-0.0.0.dist-info/top_level.txt
pygpib-0.0.0.dist-info/RECORD
