Metadata-Version: 2.1
Name: pygpib
Version: 0.0.0
Summary: Take control of your GPIB adapters!
Home-page: https://github.com/mrnuke/pygpib
Author: Alexandru Gagniuc
License: GPLv3
Keywords: GPIB,USB
Platform: UNKNOWN
Classifier: Development Status :: 1 - Planning
Classifier: Intended Audience :: Developers
Classifier: Intended Audience :: Science/Research
Classifier: Topic :: Scientific/Engineering
Classifier: License :: OSI Approved :: GNU General Public License v3 (GPLv3)
Classifier: Programming Language :: Python :: 3.7
Requires-Python: >=3.7
Requires-Dist: pyusb
